pywrfkit/__init__.py
pywrfkit/ahps.py
pywrfkit/coast.py
pywrfkit/download.py
pywrfkit/metrics.py
pywrfkit/norms.py
pywrfkit/params.py
pywrfkit/plot_geog.py
pywrfkit/polar.py
pywrfkit/wrf.py
pywrfkit/xrvar.py
pywrfkit-0.1.5.dist-info/licenses/LICENSE
pywrfkit-0.1.5.dist-info/METADATA
pywrfkit-0.1.5.dist-info/WHEEL
pywrfkit-0.1.5.dist-info/top_level.txt
pywrfkit-0.1.5.dist-info/RECORD
