Metadata-Version: 2.4
Name: pywrfkit
Version: 0.1.5
Summary: A comprehensive Python toolkit for Weather Research and Forecasting (WRF) model data processing, analysis, and visualization
Home-page: https://github.com/ankurk017/pywrfkit
Author: Ankur Kumar
Author-email: Ankur Kumar <ankurk017@gmail.com>
Maintainer-email: Ankur Kumar <ankurk017@gmail.com>
License: MIT
Project-URL: Homepage, https://github.com/ankurk017/pywrfkit
Project-URL: Documentation, https://github.com/ankurk017/pywrfkit#readme
Project-URL: Repository, https://github.com/ankurk017/pywrfkit
Project-URL: Bug Tracker, https://github.com/ankurk017/pywrfkit/issues
Keywords: wrf,weather,forecasting,meteorology,climate,atmospheric science
Classifier: Development Status :: 3 - Alpha
Classifier: Intended Audience :: Science/Research
Classifier: Topic :: Scientific/Engineering :: Atmospheric Science
Classifier: Topic :: Scientific/Engineering :: Information Analysis
Classifier: Topic :: Scientific/Engineering :: Visualization
Classifier: Programming Language :: Python :: 3
Classifier: Programming Language :: Python :: 3.8
Classifier: Programming Language :: Python :: 3.9
Classifier: Programming Language :: Python :: 3.10
Classifier: Programming Language :: Python :: 3.11
Classifier: Programming Language :: Python :: 3.12
Classifier: Operating System :: OS Independent
Requires-Python: >=3.8
License-File: LICENSE
Requires-Dist: xarray>=2023.1.0
Requires-Dist: numpy>=1.21.0
Requires-Dist: matplotlib>=3.5.0
Requires-Dist: scipy>=1.9.0
Requires-Dist: pandas>=1.5.0
Requires-Dist: pyproj>=3.4.0
Provides-Extra: cartopy
Requires-Dist: cartopy>=0.21.0; extra == "cartopy"
Provides-Extra: dev
Requires-Dist: pytest>=7.0.0; extra == "dev"
Requires-Dist: pytest-cov>=4.0.0; extra == "dev"
Requires-Dist: black>=22.0.0; extra == "dev"
Requires-Dist: flake8>=5.0.0; extra == "dev"
Requires-Dist: twine>=4.0.0; extra == "dev"
Requires-Dist: build>=0.10.0; extra == "dev"
Requires-Dist: cartopy>=0.21.0; extra == "dev"
Dynamic: author
Dynamic: home-page
Dynamic: license-file
Dynamic: requires-python
